py_stonfi/__init__.py
py_stonfi/constants.py
py_stonfi/utils.py
py_stonfi/contracts/__init__.py
py_stonfi/contracts/dex/__init__.py
py_stonfi/contracts/dex/v1/__init__.py
py_stonfi/contracts/dex/v1/lp_account.py
py_stonfi/contracts/dex/v1/pool.py
py_stonfi/contracts/dex/v1/router.py
py_stonfi/contracts/farm/__init__.py
py_stonfi/contracts/jetton/__init__.py
py_stonfi/contracts/jetton/jetton_root.py
py_stonfi/contracts/jetton/jetton_wallet.py
py_stonfi/contracts/pTON/__init__.py
py_stonfi/contracts/pTON/v1.py
py_stonfi/http/__init__.py
py_stonfi/http/api_client.py
py_stonfi/types/__init__.py
py_stonfi/types/http/__init__.py
py_stonfi/types/http/assets.py
py_stonfi/types/http/farms.py
py_stonfi/types/http/pools.py
py_stonfi/types/http/swap.py
py_stonfi-1.0.dist-info/LICENSE
py_stonfi-1.0.dist-info/METADATA
py_stonfi-1.0.dist-info/WHEEL
py_stonfi-1.0.dist-info/top_level.txt
py_stonfi-1.0.dist-info/RECORD
