Metadata-Version: 2.1
Name: py-stonfi
Version: 1.0
Summary: Asynchronous Python SDK for StonFi
Author-email: "gkozyrev (George Kozyrev)" <me@gkozyrev.ru>
Project-URL: Homepage, https://github.com/gkozyrev/py-stonfi
Classifier: Development Status :: 4 - Beta
Classifier: Intended Audience :: Developers
Classifier: Programming Language :: Python :: 3.10
Classifier: Programming Language :: Python :: 3.11
Classifier: Programming Language :: Python :: 3.12
Classifier: License :: OSI Approved :: GNU General Public License v3 (GPLv3)
Classifier: Topic :: Software Development :: Libraries
Classifier: Topic :: Software Development :: Libraries :: Python Modules
Classifier: Typing :: Typed
License-File: LICENSE
Requires-Dist: pytoniq
Requires-Dist: aiohttp
Requires-Dist: async-lru
